lib/__init__.py
lib/client.py
lib/plot.py
lib/ta.py
lib/proto/__init__.py
lib/proto/ohlcv_pb2.py
lib/proto/ohlcv_pb2_grpc.py
qpace/__init__.py
qpace/client.py
qpace/plot.py
qpace/ta.py
qpace/qpace.egg-info/PKG-INFO
qpace/qpace.egg-info/SOURCES.txt
qpace/qpace.egg-info/dependency_links.txt
qpace/qpace.egg-info/requires.txt
qpace/qpace.egg-info/top_level.txt
qpace_content/__init__.py
qpace_content/_lib.abi3.so
qpace_content/ta.py
qpace_core/__init__.py
qpace_core/__init__.pyi
qpace_core/py.typed
qpace_core/qpace_core.abi3.so
qpace-0.2.9.dist-info/LICENSE.md
qpace-0.2.9.dist-info/METADATA
qpace-0.2.9.dist-info/WHEEL
qpace-0.2.9.dist-info/top_level.txt
qpace-0.2.9.dist-info/RECORD
