Metadata-Version: 2.1
Name: qpace
Version: 0.2.9
Summary: 📊 The Quant SDK for Python and Javascript. Written in Rust.
Home-page: https://qpace.dev
Author: Nersent
Project-URL: Homepage, https://qpace.dev
Project-URL: Source, https://github.com/nersent/qpace
Requires-Python: >=3.10
License-File: LICENSE.md
